configs/__init__.py
configs/log_config.py
consts/__init__.py
consts/common_vars.py
consts/config_vars.py
models/__init__.py
models/nc_query_objs.py
models/nc_result_objs.py
service/__init__.py
service/query_nc_service.py
utils/__init__.py
utils/common_util.py
utils/nc_query_util.py
highlyQuery-0.1.0.dist-info/LICENSE
highlyQuery-0.1.0.dist-info/METADATA
highlyQuery-0.1.0.dist-info/WHEEL
highlyQuery-0.1.0.dist-info/top_level.txt
highlyQuery-0.1.0.dist-info/RECORD
