Metadata-Version: 2.1
Name: highlyQuery
Version: 0.1.0
Summary: My short description for my project.
Home-page: https://gitee.com/yingzi1/highlyquery.git
Author: Yue Jiang
Author-email: 1003383587@qq.com
License: MIT
Classifier: License :: OSI Approved :: MIT License
Classifier: Programming Language :: Python
Classifier: Programming Language :: Python :: 3
Classifier: Programming Language :: Python :: 3.9
Classifier: Programming Language :: Python :: Implementation :: CPython
Classifier: Programming Language :: Python :: Implementation :: PyPy
Requires-Python: >=3.9.0
License-File: LICENSE
